{
  "meta": {
    "type": "WorshipSongData",
    "version": 1
  },
  "tamilSegments": [
    {
      "start": 0.001,
      "end": 47.146,
      "lyrics": [
        "1. இயேசு ரத்தமே ரத்தமே ரத்தமே",
        "இயேசு ரத்தமே ரத்தமே ரத்தமே",
        "விலையேற பெற்ற ரத்தமே",
        "குற்றம் இல்லா பரிசுத்த ரத்தமே",
        "விலையேற பெற்ற ரத்தமே",
        "குற்றம் இல்லா பரிசுத்த ரத்தமே",
        "இயேசு ரத்தமே ரத்தமே ரத்தமே",
        "இயேசு ரத்தமே ரத்தமே ரத்தமே",
        "இயேசு ரத்தமே ரத்தமே ரத்தமே",
        "இயேசு ரத்தமே ரத்தமே ரத்தமே"
      ]
    },
    {
      "start": 47.147,
      "end": 121.163,
      "lyrics": [
        "2. மகாகொடூர பாவங்கள் கழுவிடும் – நம்",
        "இயேசுவின் ரத்தமே",
        "மகாகொடூர பாவங்கள் கழுவிடும் – நம்",
        "இயேசுவின் ரத்தமே",
        "மகா பிரதான ஆசாரியராய்",
        "நமக்கு முன் சென்ற பரிசுத்தரே",
        "மகா பிரதான ஆசாரியராய்",
        "நமக்கு முன் சென்ற பரிசுத்தரே",
        "இயேசு ரத்தமே ரத்தமே ரத்தமே",
        "இயேசு ரத்தமே ரத்தமே ரத்தமே",
        "விலையேற பெற்ற ரத்தமே",
        "குற்றம் இல்லா பரிசுத்த ரத்தமே",
        "விலையேற பெற்ற ரத்தமே",
        "குற்றம் இல்லா பரிசுத்த ரத்தமே",
        "இயேசு ரத்தமே ரத்தமே ரத்தமே",
        "இயேசு ரத்தமே ரத்தமே ரத்தமே"
      ]
    },
    {
      "start": 121.164,
      "end": 200.029,
      "lyrics": [
        "3. மனசாட்சியை சுத்திகரித்திடும் – நம்",
        "இயேசுவின் ரத்தமே",
        "மனசாட்சியை சுத்திகரித்திடும் – நம்",
        "இயேசுவின் ரத்தமே",
        "மனவேதனை நீக்கிடுமே",
        "சாபமெல்லாமே போக்கிடுமே",
        "மனவேதனை நீக்கிடுமே",
        "சாபமெல்லாமே போக்கிடுமே",
        "இயேசு ரத்தமே ரத்தமே ரத்தமே",
        "இயேசு ரத்தமே ரத்தமே ரத்தமே",
        "விலையேற பெற்ற ரத்தமே",
        "குற்றம் இல்லா பரிசுத்த ரத்தமே",
        "விலையேற பெற்ற ரத்தமே",
        "குற்றம் இல்லா பரிசுத்த ரத்தமே",
        "இயேசு ரத்தமே ரத்தமே ரத்தமே",
        "இயேசு ரத்தமே ரத்தமே ரத்தமே",
        "இயேசு ரத்தமே ரத்தமே ரத்தமே",
        "இயேசு ரத்தமே ரத்தமே ரத்தமே"
      ]
    }
  ],
  "englishLyrics": [
    "Segment 1",
    "Yesu raththame raththame raththame",
    "Vilaiyera petra raththame",
    "Kutram illaa parisutha raththame",
    "yesu raththame raththame raththame",
    "Segment 2",
    "Magaa kodura paavangal kazhuvidum – nam",
    "yesuvin raththame",
    "Magaa viyaakula vedhanaiyaai viyarvai",
    "raththamaai veli vanthadhe",
    "Segment 3",
    "Manasaatchiyai suththikarithidum – nam",
    "yesuvin raththame",
    "Manavedhanai neengidume",
    "Saabam ellaame pokkidume",
    "Magaa parisutha sthalamathil saerthidum",
    "Nam yesuvin raththame",
    "Magaa pradhaana aasaariyaraai",
    "Namakku mun sendra parisuththarae"
  ]
}