{
  "meta": {
    "type": "WorshipSongData",
    "version": 1
  },
  "tamilSegments": [
    {
      "start": 42.478,
      "end": 88.084,
      "lyrics": [
        "தேவனுக்கே மகிமை தெய்வத்திற்கே மகிமை 1T",
        "தேவனுக்கே மகிமை தெய்வத்திற்கே மகிமை 2T",
        "தேடி வந்து மீட்டவரே தினம் உமக்கே மகிமை 1T என்னை",
        "தேடி வந்து மீட்டவரே தினம் உமக்கே மகிமை 2T",
        "ஐயா வாழ்க வாழ்க உம்நாமம் வாழ்க 1T",
        "ஐயா வாழ்க வாழ்க உம்நாமம் வாழ்க 2T"
      ]
    },
    {
      "start": 107.724,
      "end": 168.714,
      "lyrics": [
        "உன்னத்தில் தேவனுக்கே",
        "மகிமை உண்டாகட்டும் 1T",
        "உன்னத்தில் தேவனுக்கே",
        "மகிமை உண்டாகட்டும் 2T",
        "பூமியிலே சமாதானமும்",
        "பிரியமும் உண்டாகட்டும் 1T இந்தப்",
        "பூமியிலே சமாதானமும்",
        "பிரியமும் உண்டாகட்டும் 2T",
        "ஐயா வாழ்க வாழ்க உம்நாமம் வாழ்க 1T",
        "ஐயா வாழ்க வாழ்க உம்நாமம் வாழ்க 2T",
        "தேவனுக்கே மகிமை தெய்வத்திற்கே மகிமை 1T",
        "தேடி வந்து மீட்டவரே தினம் உமக்கே மகிமை 1T"
      ]
    },
    {
      "start": 188.428,
      "end": 249.525,
      "lyrics": [
        "செவிகளை நீர் திறந்து விட்டீர்",
        "செய்வோம் உம் சித்தம்  1T",
        "செவிகளை நீர் திறந்து விட்டீர்",
        "செய்வோம் உம் சித்தம்  2T",
        "புவிதனிலே உம் விருப்பம்",
        "பூரணமாகட்டுமே 1T இந்தப்",
        "புவிதனிலே உம் விருப்பம்",
        "பூரணமாகட்டுமே 2T",
        "ஐயா வாழ்க வாழ்க உம்நாமம் வாழ்க 1T",
        "ஐயா வாழ்க வாழ்க உம்நாமம் வாழ்க 2T",
        "தேவனுக்கே மகிமை தெய்வத்திற்கே மகிமை 1T",
        "தேடி வந்து மீட்டவரே தினம் உமக்கே மகிமை 1T"
      ]
    },
    {
      "start": 284.379,
      "end": 345.309,
      "lyrics": [
        "எளிமையான எங்களையே",
        "என்றும் நினைப்பவரே 1T",
        "எளிமையான எங்களையே",
        "என்றும் நினைப்பவரே 2T",
        "ஒளிமயமே துணையாளரே",
        "உள்ளத்தின் ஆறுதலே 1T எங்கள்",
        "ஒளிமயமே துணையாளரே",
        "உள்ளத்தின் ஆறுதலே 2T",
        "ஐயா வாழ்க வாழ்க உம்நாமம் வாழ்க 1T",
        "ஐயா வாழ்க வாழ்க உம்நாமம் வாழ்க 2T",
        "தேவனுக்கே மகிமை தெய்வத்திற்கே மகிமை 1T",
        "தேடி வந்து மீட்டவரே தினம் உமக்கே மகிமை 1T"
      ]
    },
    {
      "start": 364.948,
      "end": 445.656,
      "lyrics": [
        "தேடுகிற அனைவருமே",
        "மகிழ்ந்து களிகூரட்டும் 1T",
        "தேடுகிற அனைவருமே",
        "மகிழ்ந்து களிகூரட்டும் 2T",
        "பாடுகிற யாவருமே",
        "பரிசுத்தம் ஆகட்டுமே 1T இன்று",
        "பாடுகிற யாவருமே",
        "பரிசுத்தம் ஆகட்டுமே 2T",
        "ஐயா வாழ்க வாழ்க உம்நாமம் வாழ்க 1T",
        "ஐயா வாழ்க வாழ்க உம்நாமம் வாழ்க 2T",
        "தேவனுக்கே மகிமை தெய்வத்திற்கே மகிமை 1T",
        "தேடி வந்து மீட்டவரே தினம் உமக்கே மகிமை 1T",
        "ஐயா வாழ்க வாழ்க உம்நாமம் வாழ்க 1T",
        "ஐயா வாழ்க வாழ்க உம்நாமம் வாழ்க 2T"
      ]
    }
  ],
  "englishSegments": [
    {
      "start": 42.478,
      "end": 88.084,
      "lyrics": [
        "Devanuke Magimai",
        "thaevanukkae makimai theyvaththirkae makimai",
        "thaeti vanthu meettavarae thinam umakkae makimai",
        "aiyaa vaalka vaalka umnaamam vaalka"
      ]
    },
    {
      "start": 107.724,
      "end": 168.714,
      "lyrics": [
        "Unnaththil thaevanukkae",
        "makimai unndaakattum - inthap",
        "poomiyilae samaathaanamum",
        "piriyamum unndaakattum - aiyaa"
      ]
    },
    {
      "start": 188.428,
      "end": 249.525,
      "lyrics": [
        "Sevikalai neer thiranthu vittir",
        "seyvom um siththam - inthap",
        "puvithanil um viruppam",
        "pooranamaakattum - aiyaa"
      ]
    },
    {
      "start": 284.379,
      "end": 345.309,
      "lyrics": [
        "Elimaiyaana engalaiyae",
        "entum ninaippavarae - engal",
        "olimayamae thunnaiyaalarae",
        "ullaththin aaruthalae - aiyaa"
      ]
    },
    {
      "start": 364.948,
      "end": 445.656,
      "lyrics": [
        "Thaedukira anaivarumae",
        "makilnthu kalikoorattum - intu",
        "paadukira yaavarumae",
        "parisuththam aakattumae - aiyaa",
        "5. kurai neekkum vallavarae",
        "koti sthoththiramae - paavak",
        "karaipokkum karththaavae",
        "kalvaari naayakanae - aiyaa",
        "5. குறை நீக்கும் வல்லவரே",
        "கோடி ஸ்தோத்திரமே – பாவக்",
        "கறைபோக்கும் கர்த்தாவே",
        "கல்வாரி நாயகனே – ஐயா"
      ]
    }
  ]
}